<Objs Version="1.1.0.1" xmlns="http://schemas.microsoft.com/powershell/2004/04">
  <Obj RefId="0">
    <TN RefId="0">
      <T>Microsoft.PowerShell.Commands.PSRepositoryItemInfo</T>
      <T>System.Management.Automation.PSCustomObject</T>
      <T>System.Object</T>
    </TN>
    <MS>
      <S N="Name">Microsoft.Graph.Identity.DirectoryManagement</S>
      <S N="Version">2.25.0</S>
      <S N="Type">Module</S>
      <S N="Description">Microsoft Graph PowerShell Cmdlets</S>
      <S N="Author">Microsoft Corporation</S>
      <S N="CompanyName">msgraph-sdk-powershell</S>
      <S N="Copyright">Microsoft Corporation. All rights reserved.</S>
      <DT N="PublishedDate">2024-11-21T06:27:58-05:00</DT>
      <Nil N="InstalledDate" />
      <Nil N="UpdatedDate" />
      <URI N="LicenseUri">https://aka.ms/devservicesagreement</URI>
      <URI N="ProjectUri">https://github.com/microsoftgraph/msgraph-sdk-powershell</URI>
      <URI N="IconUri">https://raw.githubusercontent.com/microsoftgraph/msgraph-sdk-powershell/dev/docs/images/graph_color256.png</URI>
      <Obj N="Tags" RefId="1">
        <TN RefId="1">
          <T>System.Object[]</T>
          <T>System.Array</T>
          <T>System.Object</T>
        </TN>
        <LST>
          <S>Microsoft</S>
          <S>Office365</S>
          <S>Graph</S>
          <S>PowerShell</S>
          <S>PSModule</S>
          <S>PSEdition_Core</S>
          <S>PSEdition_Desktop</S>
        </LST>
      </Obj>
      <Obj N="Includes" RefId="2">
        <TN RefId="2">
          <T>System.Collections.Hashtable</T>
          <T>System.Object</T>
        </TN>
        <DCT>
          <En>
            <S N="Key">Function</S>
            <Obj N="Value" RefId="3">
              <TNRef RefId="1" />
              <LST>
                <S>Confirm-MgContactMemberGroup</S>
                <S>Confirm-MgContactMemberObject</S>
                <S>Confirm-MgContractMemberGroup</S>
                <S>Confirm-MgContractMemberObject</S>
                <S>Confirm-MgDeviceMemberGroup</S>
                <S>Confirm-MgDeviceMemberObject</S>
                <S>Confirm-MgDirectoryDeletedItemMemberGroup</S>
                <S>Confirm-MgDirectoryDeletedItemMemberObject</S>
                <S>Confirm-MgDirectoryRoleMemberGroup</S>
                <S>Confirm-MgDirectoryRoleMemberObject</S>
                <S>Confirm-MgDirectoryRoleTemplateMemberGroup</S>
                <S>Confirm-MgDirectoryRoleTemplateMemberObject</S>
                <S>Confirm-MgDomain</S>
                <S>Confirm-MgOrganizationMemberGroup</S>
                <S>Confirm-MgOrganizationMemberObject</S>
                <S>Get-MgAdminPeople</S>
                <S>Get-MgAdminPeopleItemInsight</S>
                <S>Get-MgAdminPeopleProfileCardProperty</S>
                <S>Get-MgAdminPeopleProfileCardPropertyCount</S>
                <S>Get-MgAdminPeoplePronoun</S>
                <S>Get-MgContact</S>
                <S>Get-MgContactById</S>
                <S>Get-MgContactCount</S>
                <S>Get-MgContactDelta</S>
                <S>Get-MgContactDirectReport</S>
                <S>Get-MgContactDirectReportAsOrgContact</S>
                <S>Get-MgContactDirectReportAsUser</S>
                <S>Get-MgContactDirectReportCount</S>
                <S>Get-MgContactDirectReportCountAsOrgContact</S>
                <S>Get-MgContactDirectReportCountAsUser</S>
                <S>Get-MgContactManager</S>
                <S>Get-MgContactMemberGroup</S>
                <S>Get-MgContactMemberObject</S>
                <S>Get-MgContactMemberOf</S>
                <S>Get-MgContactMemberOfAsAdministrativeUnit</S>
                <S>Get-MgContactMemberOfAsGroup</S>
                <S>Get-MgContactMemberOfCount</S>
                <S>Get-MgContactMemberOfCountAsAdministrativeUnit</S>
                <S>Get-MgContactMemberOfCountAsGroup</S>
                <S>Get-MgContactServiceProvisioningError</S>
                <S>Get-MgContactServiceProvisioningErrorCount</S>
                <S>Get-MgContactTransitiveMemberOf</S>
                <S>Get-MgContactTransitiveMemberOfAsAdministrativeUnit</S>
                <S>Get-MgContactTransitiveMemberOfAsGroup</S>
                <S>Get-MgContactTransitiveMemberOfCount</S>
                <S>Get-MgContactTransitiveMemberOfCountAsAdministrativeUnit</S>
                <S>Get-MgContactTransitiveMemberOfCountAsGroup</S>
                <S>Get-MgContract</S>
                <S>Get-MgContractById</S>
                <S>Get-MgContractCount</S>
                <S>Get-MgContractDelta</S>
                <S>Get-MgContractMemberGroup</S>
                <S>Get-MgContractMemberObject</S>
                <S>Get-MgDevice</S>
                <S>Get-MgDeviceByDeviceId</S>
                <S>Get-MgDeviceById</S>
                <S>Get-MgDeviceCount</S>
                <S>Get-MgDeviceDelta</S>
                <S>Get-MgDeviceExtension</S>
                <S>Get-MgDeviceExtensionCount</S>
                <S>Get-MgDeviceMemberGroup</S>
                <S>Get-MgDeviceMemberObject</S>
                <S>Get-MgDeviceMemberOf</S>
                <S>Get-MgDeviceMemberOfAsAdministrativeUnit</S>
                <S>Get-MgDeviceMemberOfAsGroup</S>
                <S>Get-MgDeviceMemberOfCount</S>
                <S>Get-MgDeviceMemberOfCountAsAdministrativeUnit</S>
                <S>Get-MgDeviceMemberOfCountAsGroup</S>
                <S>Get-MgDeviceRegisteredOwner</S>
                <S>Get-MgDeviceRegisteredOwnerAsAppRoleAssignment</S>
                <S>Get-MgDeviceRegisteredOwnerAsEndpoint</S>
                <S>Get-MgDeviceRegisteredOwnerAsServicePrincipal</S>
                <S>Get-MgDeviceRegisteredOwnerAsUser</S>
                <S>Get-MgDeviceRegisteredOwnerByRef</S>
                <S>Get-MgDeviceRegisteredOwnerCount</S>
                <S>Get-MgDeviceRegisteredOwnerCountAsAppRoleAssignment</S>
                <S>Get-MgDeviceRegisteredOwnerCountAsEndpoint</S>
                <S>Get-MgDeviceRegisteredOwnerCountAsServicePrincipal</S>
                <S>Get-MgDeviceRegisteredOwnerCountAsUser</S>
                <S>Get-MgDeviceRegisteredUser</S>
                <S>Get-MgDeviceRegisteredUserAsAppRoleAssignment</S>
                <S>Get-MgDeviceRegisteredUserAsEndpoint</S>
                <S>Get-MgDeviceRegisteredUserAsServicePrincipal</S>
                <S>Get-MgDeviceRegisteredUserAsUser</S>
                <S>Get-MgDeviceRegisteredUserByRef</S>
                <S>Get-MgDeviceRegisteredUserCount</S>
                <S>Get-MgDeviceRegisteredUserCountAsAppRoleAssignment</S>
                <S>Get-MgDeviceRegisteredUserCountAsEndpoint</S>
                <S>Get-MgDeviceRegisteredUserCountAsServicePrincipal</S>
                <S>Get-MgDeviceRegisteredUserCountAsUser</S>
                <S>Get-MgDeviceTransitiveMemberOf</S>
                <S>Get-MgDeviceTransitiveMemberOfAsAdministrativeUnit</S>
                <S>Get-MgDeviceTransitiveMemberOfAsGroup</S>
                <S>Get-MgDeviceTransitiveMemberOfCount</S>
                <S>Get-MgDeviceTransitiveMemberOfCountAsAdministrativeUnit</S>
                <S>Get-MgDeviceTransitiveMemberOfCountAsGroup</S>
                <S>Get-MgDirectory</S>
                <S>Get-MgDirectoryAdministrativeUnit</S>
                <S>Get-MgDirectoryAdministrativeUnitCount</S>
                <S>Get-MgDirectoryAdministrativeUnitDelta</S>
                <S>Get-MgDirectoryAdministrativeUnitExtension</S>
                <S>Get-MgDirectoryAdministrativeUnitExtensionCount</S>
                <S>Get-MgDirectoryAdministrativeUnitMember</S>
                <S>Get-MgDirectoryAdministrativeUnitMemberAsApplication</S>
                <S>Get-MgDirectoryAdministrativeUnitMemberAsDevice</S>
                <S>Get-MgDirectoryAdministrativeUnitMemberAsGroup</S>
                <S>Get-MgDirectoryAdministrativeUnitMemberAsOrgContact</S>
                <S>Get-MgDirectoryAdministrativeUnitMemberAsServicePrincipal</S>
                <S>Get-MgDirectoryAdministrativeUnitMemberAsUser</S>
                <S>Get-MgDirectoryAdministrativeUnitMemberByRef</S>
                <S>Get-MgDirectoryAdministrativeUnitMemberCount</S>
                <S>Get-MgDirectoryAdministrativeUnitMemberCountAsApplication</S>
                <S>Get-MgDirectoryAdministrativeUnitMemberCountAsDevice</S>
                <S>Get-MgDirectoryAdministrativeUnitMemberCountAsGroup</S>
                <S>Get-MgDirectoryAdministrativeUnitMemberCountAsOrgContact</S>
                <S>Get-MgDirectoryAdministrativeUnitMemberCountAsServicePrincipal</S>
                <S>Get-MgDirectoryAdministrativeUnitMemberCountAsUser</S>
                <S>Get-MgDirectoryAdministrativeUnitScopedRoleMember</S>
                <S>Get-MgDirectoryAdministrativeUnitScopedRoleMemberCount</S>
                <S>Get-MgDirectoryAttributeSet</S>
                <S>Get-MgDirectoryAttributeSetCount</S>
                <S>Get-MgDirectoryCustomSecurityAttributeDefinition</S>
                <S>Get-MgDirectoryCustomSecurityAttributeDefinitionAllowedValue</S>
                <S>Get-MgDirectoryCustomSecurityAttributeDefinitionAllowedValueCount</S>
                <S>Get-MgDirectoryCustomSecurityAttributeDefinitionCount</S>
                <S>Get-MgDirectoryDeletedItem</S>
                <S>Get-MgDirectoryDeletedItemAsAdministrativeUnit</S>
                <S>Get-MgDirectoryDeletedItemAsApplication</S>
                <S>Get-MgDirectoryDeletedItemAsDevice</S>
                <S>Get-MgDirectoryDeletedItemAsGroup</S>
                <S>Get-MgDirectoryDeletedItemAsServicePrincipal</S>
                <S>Get-MgDirectoryDeletedItemAsUser</S>
                <S>Get-MgDirectoryDeletedItemById</S>
                <S>Get-MgDirectoryDeletedItemCountAsAdministrativeUnit</S>
                <S>Get-MgDirectoryDeletedItemCountAsApplication</S>
                <S>Get-MgDirectoryDeletedItemCountAsDevice</S>
                <S>Get-MgDirectoryDeletedItemCountAsGroup</S>
                <S>Get-MgDirectoryDeletedItemCountAsServicePrincipal</S>
                <S>Get-MgDirectoryDeletedItemCountAsUser</S>
                <S>Get-MgDirectoryDeletedItemMemberGroup</S>
                <S>Get-MgDirectoryDeletedItemMemberObject</S>
                <S>Get-MgDirectoryDeviceLocalCredential</S>
                <S>Get-MgDirectoryDeviceLocalCredentialCount</S>
                <S>Get-MgDirectoryFederationConfiguration</S>
                <S>Get-MgDirectoryFederationConfigurationCount</S>
                <S>Get-MgDirectoryOnPremiseSynchronization</S>
                <S>Get-MgDirectoryOnPremiseSynchronizationCount</S>
                <S>Get-MgDirectoryRole</S>
                <S>Get-MgDirectoryRoleById</S>
                <S>Get-MgDirectoryRoleByRoleTemplateId</S>
                <S>Get-MgDirectoryRoleCount</S>
                <S>Get-MgDirectoryRoleDelta</S>
                <S>Get-MgDirectoryRoleMember</S>
                <S>Get-MgDirectoryRoleMemberAsApplication</S>
                <S>Get-MgDirectoryRoleMemberAsDevice</S>
                <S>Get-MgDirectoryRoleMemberAsGroup</S>
                <S>Get-MgDirectoryRoleMemberAsOrgContact</S>
                <S>Get-MgDirectoryRoleMemberAsServicePrincipal</S>
                <S>Get-MgDirectoryRoleMemberAsUser</S>
                <S>Get-MgDirectoryRoleMemberByRef</S>
                <S>Get-MgDirectoryRoleMemberCount</S>
                <S>Get-MgDirectoryRoleMemberCountAsApplication</S>
                <S>Get-MgDirectoryRoleMemberCountAsDevice</S>
                <S>Get-MgDirectoryRoleMemberCountAsGroup</S>
                <S>Get-MgDirectoryRoleMemberCountAsOrgContact</S>
                <S>Get-MgDirectoryRoleMemberCountAsServicePrincipal</S>
                <S>Get-MgDirectoryRoleMemberCountAsUser</S>
                <S>Get-MgDirectoryRoleMemberGroup</S>
                <S>Get-MgDirectoryRoleMemberObject</S>
                <S>Get-MgDirectoryRoleScopedMember</S>
                <S>Get-MgDirectoryRoleScopedMemberCount</S>
                <S>Get-MgDirectoryRoleTemplate</S>
                <S>Get-MgDirectoryRoleTemplateById</S>
                <S>Get-MgDirectoryRoleTemplateCount</S>
                <S>Get-MgDirectoryRoleTemplateDelta</S>
                <S>Get-MgDirectoryRoleTemplateMemberGroup</S>
                <S>Get-MgDirectoryRoleTemplateMemberObject</S>
                <S>Get-MgDirectorySubscription</S>
                <S>Get-MgDirectorySubscriptionByCommerceSubscriptionId</S>
                <S>Get-MgDirectorySubscriptionCount</S>
                <S>Get-MgDomain</S>
                <S>Get-MgDomainCount</S>
                <S>Get-MgDomainFederationConfiguration</S>
                <S>Get-MgDomainFederationConfigurationCount</S>
                <S>Get-MgDomainNameReference</S>
                <S>Get-MgDomainNameReferenceCount</S>
                <S>Get-MgDomainRootDomain</S>
                <S>Get-MgDomainServiceConfigurationRecord</S>
                <S>Get-MgDomainServiceConfigurationRecordCount</S>
                <S>Get-MgDomainVerificationDnsRecord</S>
                <S>Get-MgDomainVerificationDnsRecordCount</S>
                <S>Get-MgOrganization</S>
                <S>Get-MgOrganizationBranding</S>
                <S>Get-MgOrganizationBrandingBackgroundImage</S>
                <S>Get-MgOrganizationBrandingBannerLogo</S>
                <S>Get-MgOrganizationBrandingCustomCss</S>
                <S>Get-MgOrganizationBrandingFavicon</S>
                <S>Get-MgOrganizationBrandingHeaderLogo</S>
                <S>Get-MgOrganizationBrandingLocalization</S>
                <S>Get-MgOrganizationBrandingLocalizationBackgroundImage</S>
                <S>Get-MgOrganizationBrandingLocalizationBannerLogo</S>
                <S>Get-MgOrganizationBrandingLocalizationCount</S>
                <S>Get-MgOrganizationBrandingLocalizationCustomCss</S>
                <S>Get-MgOrganizationBrandingLocalizationFavicon</S>
                <S>Get-MgOrganizationBrandingLocalizationHeaderLogo</S>
                <S>Get-MgOrganizationBrandingLocalizationSquareLogo</S>
                <S>Get-MgOrganizationBrandingLocalizationSquareLogoDark</S>
                <S>Get-MgOrganizationBrandingSquareLogo</S>
                <S>Get-MgOrganizationBrandingSquareLogoDark</S>
                <S>Get-MgOrganizationById</S>
                <S>Get-MgOrganizationCount</S>
                <S>Get-MgOrganizationExtension</S>
                <S>Get-MgOrganizationExtensionCount</S>
                <S>Get-MgOrganizationMemberGroup</S>
                <S>Get-MgOrganizationMemberObject</S>
                <S>Get-MgSubscribedSku</S>
                <S>Get-MgUserScopedRoleMemberOf</S>
                <S>Get-MgUserScopedRoleMemberOfCount</S>
                <S>Invoke-MgAvailableDirectoryFederationConfigurationProviderType</S>
                <S>Invoke-MgForceDomainDelete</S>
                <S>Invoke-MgPromoteDomain</S>
                <S>Invoke-MgRetryContactServiceProvisioning</S>
                <S>New-MgAdminPeopleProfileCardProperty</S>
                <S>New-MgContact</S>
                <S>New-MgContract</S>
                <S>New-MgDevice</S>
                <S>New-MgDeviceExtension</S>
                <S>New-MgDeviceRegisteredOwnerByRef</S>
                <S>New-MgDeviceRegisteredUserByRef</S>
                <S>New-MgDirectoryAdministrativeUnit</S>
                <S>New-MgDirectoryAdministrativeUnitExtension</S>
                <S>New-MgDirectoryAdministrativeUnitMember</S>
                <S>New-MgDirectoryAdministrativeUnitMemberByRef</S>
                <S>New-MgDirectoryAdministrativeUnitScopedRoleMember</S>
                <S>New-MgDirectoryAttributeSet</S>
                <S>New-MgDirectoryCustomSecurityAttributeDefinition</S>
                <S>New-MgDirectoryCustomSecurityAttributeDefinitionAllowedValue</S>
                <S>New-MgDirectoryDeviceLocalCredential</S>
                <S>New-MgDirectoryFederationConfiguration</S>
                <S>New-MgDirectoryOnPremiseSynchronization</S>
                <S>New-MgDirectoryRole</S>
                <S>New-MgDirectoryRoleMemberByRef</S>
                <S>New-MgDirectoryRoleScopedMember</S>
                <S>New-MgDirectoryRoleTemplate</S>
                <S>New-MgDirectorySubscription</S>
                <S>New-MgDomain</S>
                <S>New-MgDomainFederationConfiguration</S>
                <S>New-MgDomainServiceConfigurationRecord</S>
                <S>New-MgDomainVerificationDnsRecord</S>
                <S>New-MgOrganization</S>
                <S>New-MgOrganizationBrandingLocalization</S>
                <S>New-MgOrganizationExtension</S>
                <S>New-MgSubscribedSku</S>
                <S>New-MgUserScopedRoleMemberOf</S>
                <S>Remove-MgAdminPeopleItemInsight</S>
                <S>Remove-MgAdminPeopleProfileCardProperty</S>
                <S>Remove-MgContact</S>
                <S>Remove-MgContract</S>
                <S>Remove-MgDevice</S>
                <S>Remove-MgDeviceByDeviceId</S>
                <S>Remove-MgDeviceExtension</S>
                <S>Remove-MgDeviceRegisteredOwnerDirectoryObjectByRef</S>
                <S>Remove-MgDeviceRegisteredUserDirectoryObjectByRef</S>
                <S>Remove-MgDirectoryAdministrativeUnit</S>
                <S>Remove-MgDirectoryAdministrativeUnitExtension</S>
                <S>Remove-MgDirectoryAdministrativeUnitMemberDirectoryObjectByRef</S>
                <S>Remove-MgDirectoryAdministrativeUnitScopedRoleMember</S>
                <S>Remove-MgDirectoryAttributeSet</S>
                <S>Remove-MgDirectoryCustomSecurityAttributeDefinition</S>
                <S>Remove-MgDirectoryCustomSecurityAttributeDefinitionAllowedValue</S>
                <S>Remove-MgDirectoryDeletedItem</S>
                <S>Remove-MgDirectoryDeviceLocalCredential</S>
                <S>Remove-MgDirectoryFederationConfiguration</S>
                <S>Remove-MgDirectoryOnPremiseSynchronization</S>
                <S>Remove-MgDirectoryRole</S>
                <S>Remove-MgDirectoryRoleByRoleTemplateId</S>
                <S>Remove-MgDirectoryRoleMemberDirectoryObjectByRef</S>
                <S>Remove-MgDirectoryRoleScopedMember</S>
                <S>Remove-MgDirectoryRoleTemplate</S>
                <S>Remove-MgDirectorySubscription</S>
                <S>Remove-MgDirectorySubscriptionByCommerceSubscriptionId</S>
                <S>Remove-MgDomain</S>
                <S>Remove-MgDomainFederationConfiguration</S>
                <S>Remove-MgDomainServiceConfigurationRecord</S>
                <S>Remove-MgDomainVerificationDnsRecord</S>
                <S>Remove-MgOrganization</S>
                <S>Remove-MgOrganizationBranding</S>
                <S>Remove-MgOrganizationBrandingBackgroundImage</S>
                <S>Remove-MgOrganizationBrandingBannerLogo</S>
                <S>Remove-MgOrganizationBrandingCustomCss</S>
                <S>Remove-MgOrganizationBrandingFavicon</S>
                <S>Remove-MgOrganizationBrandingHeaderLogo</S>
                <S>Remove-MgOrganizationBrandingLocalization</S>
                <S>Remove-MgOrganizationBrandingLocalizationBackgroundImage</S>
                <S>Remove-MgOrganizationBrandingLocalizationBannerLogo</S>
                <S>Remove-MgOrganizationBrandingLocalizationCustomCss</S>
                <S>Remove-MgOrganizationBrandingLocalizationFavicon</S>
                <S>Remove-MgOrganizationBrandingLocalizationHeaderLogo</S>
                <S>Remove-MgOrganizationBrandingLocalizationSquareLogo</S>
                <S>Remove-MgOrganizationBrandingLocalizationSquareLogoDark</S>
                <S>Remove-MgOrganizationBrandingSquareLogo</S>
                <S>Remove-MgOrganizationBrandingSquareLogoDark</S>
                <S>Remove-MgOrganizationExtension</S>
                <S>Remove-MgSubscribedSku</S>
                <S>Remove-MgUserScopedRoleMemberOf</S>
                <S>Restore-MgDirectoryDeletedItem</S>
                <S>Set-MgOrganizationBrandingBackgroundImage</S>
                <S>Set-MgOrganizationBrandingBannerLogo</S>
                <S>Set-MgOrganizationBrandingCustomCss</S>
                <S>Set-MgOrganizationBrandingFavicon</S>
                <S>Set-MgOrganizationBrandingHeaderLogo</S>
                <S>Set-MgOrganizationBrandingLocalizationBackgroundImage</S>
                <S>Set-MgOrganizationBrandingLocalizationBannerLogo</S>
                <S>Set-MgOrganizationBrandingLocalizationCustomCss</S>
                <S>Set-MgOrganizationBrandingLocalizationFavicon</S>
                <S>Set-MgOrganizationBrandingLocalizationHeaderLogo</S>
                <S>Set-MgOrganizationBrandingLocalizationSquareLogo</S>
                <S>Set-MgOrganizationBrandingLocalizationSquareLogoDark</S>
                <S>Set-MgOrganizationBrandingSquareLogo</S>
                <S>Set-MgOrganizationBrandingSquareLogoDark</S>
                <S>Set-MgOrganizationMobileDeviceManagementAuthority</S>
                <S>Test-MgContactProperty</S>
                <S>Test-MgContractProperty</S>
                <S>Test-MgDeviceProperty</S>
                <S>Test-MgDirectoryDeletedItemProperty</S>
                <S>Test-MgDirectoryRoleProperty</S>
                <S>Test-MgDirectoryRoleTemplateProperty</S>
                <S>Test-MgOrganizationProperty</S>
                <S>Update-MgAdminPeopleItemInsight</S>
                <S>Update-MgAdminPeopleProfileCardProperty</S>
                <S>Update-MgAdminPeoplePronoun</S>
                <S>Update-MgContact</S>
                <S>Update-MgContract</S>
                <S>Update-MgDevice</S>
                <S>Update-MgDeviceByDeviceId</S>
                <S>Update-MgDeviceExtension</S>
                <S>Update-MgDirectory</S>
                <S>Update-MgDirectoryAdministrativeUnit</S>
                <S>Update-MgDirectoryAdministrativeUnitExtension</S>
                <S>Update-MgDirectoryAdministrativeUnitScopedRoleMember</S>
                <S>Update-MgDirectoryAttributeSet</S>
                <S>Update-MgDirectoryCustomSecurityAttributeDefinition</S>
                <S>Update-MgDirectoryCustomSecurityAttributeDefinitionAllowedValue</S>
                <S>Update-MgDirectoryDeviceLocalCredential</S>
                <S>Update-MgDirectoryFederationConfiguration</S>
                <S>Update-MgDirectoryOnPremiseSynchronization</S>
                <S>Update-MgDirectoryRole</S>
                <S>Update-MgDirectoryRoleByRoleTemplateId</S>
                <S>Update-MgDirectoryRoleScopedMember</S>
                <S>Update-MgDirectoryRoleTemplate</S>
                <S>Update-MgDirectorySubscription</S>
                <S>Update-MgDirectorySubscriptionByCommerceSubscriptionId</S>
                <S>Update-MgDomain</S>
                <S>Update-MgDomainFederationConfiguration</S>
                <S>Update-MgDomainServiceConfigurationRecord</S>
                <S>Update-MgDomainVerificationDnsRecord</S>
                <S>Update-MgOrganization</S>
                <S>Update-MgOrganizationBranding</S>
                <S>Update-MgOrganizationBrandingLocalization</S>
                <S>Update-MgOrganizationExtension</S>
                <S>Update-MgSubscribedSku</S>
                <S>Update-MgUserScopedRoleMemberOf</S>
              </LST>
            </Obj>
          </En>
          <En>
            <S N="Key">RoleCapability</S>
            <Obj N="Value" RefId="4">
              <TNRef RefId="1" />
              <LST />
            </Obj>
          </En>
          <En>
            <S N="Key">Command</S>
            <Obj N="Value" RefId="5">
              <TNRef RefId="1" />
              <LST>
                <S>Confirm-MgContactMemberGroup</S>
                <S>Confirm-MgContactMemberObject</S>
                <S>Confirm-MgContractMemberGroup</S>
                <S>Confirm-MgContractMemberObject</S>
                <S>Confirm-MgDeviceMemberGroup</S>
                <S>Confirm-MgDeviceMemberObject</S>
                <S>Confirm-MgDirectoryDeletedItemMemberGroup</S>
                <S>Confirm-MgDirectoryDeletedItemMemberObject</S>
                <S>Confirm-MgDirectoryRoleMemberGroup</S>
                <S>Confirm-MgDirectoryRoleMemberObject</S>
                <S>Confirm-MgDirectoryRoleTemplateMemberGroup</S>
                <S>Confirm-MgDirectoryRoleTemplateMemberObject</S>
                <S>Confirm-MgDomain</S>
                <S>Confirm-MgOrganizationMemberGroup</S>
                <S>Confirm-MgOrganizationMemberObject</S>
                <S>Get-MgAdminPeople</S>
                <S>Get-MgAdminPeopleItemInsight</S>
                <S>Get-MgAdminPeopleProfileCardProperty</S>
                <S>Get-MgAdminPeopleProfileCardPropertyCount</S>
                <S>Get-MgAdminPeoplePronoun</S>
                <S>Get-MgContact</S>
                <S>Get-MgContactById</S>
                <S>Get-MgContactCount</S>
                <S>Get-MgContactDelta</S>
                <S>Get-MgContactDirectReport</S>
                <S>Get-MgContactDirectReportAsOrgContact</S>
                <S>Get-MgContactDirectReportAsUser</S>
                <S>Get-MgContactDirectReportCount</S>
                <S>Get-MgContactDirectReportCountAsOrgContact</S>
                <S>Get-MgContactDirectReportCountAsUser</S>
                <S>Get-MgContactManager</S>
                <S>Get-MgContactMemberGroup</S>
                <S>Get-MgContactMemberObject</S>
                <S>Get-MgContactMemberOf</S>
                <S>Get-MgContactMemberOfAsAdministrativeUnit</S>
                <S>Get-MgContactMemberOfAsGroup</S>
                <S>Get-MgContactMemberOfCount</S>
                <S>Get-MgContactMemberOfCountAsAdministrativeUnit</S>
                <S>Get-MgContactMemberOfCountAsGroup</S>
                <S>Get-MgContactServiceProvisioningError</S>
                <S>Get-MgContactServiceProvisioningErrorCount</S>
                <S>Get-MgContactTransitiveMemberOf</S>
                <S>Get-MgContactTransitiveMemberOfAsAdministrativeUnit</S>
                <S>Get-MgContactTransitiveMemberOfAsGroup</S>
                <S>Get-MgContactTransitiveMemberOfCount</S>
                <S>Get-MgContactTransitiveMemberOfCountAsAdministrativeUnit</S>
                <S>Get-MgContactTransitiveMemberOfCountAsGroup</S>
                <S>Get-MgContract</S>
                <S>Get-MgContractById</S>
                <S>Get-MgContractCount</S>
                <S>Get-MgContractDelta</S>
                <S>Get-MgContractMemberGroup</S>
                <S>Get-MgContractMemberObject</S>
                <S>Get-MgDevice</S>
                <S>Get-MgDeviceByDeviceId</S>
                <S>Get-MgDeviceById</S>
                <S>Get-MgDeviceCount</S>
                <S>Get-MgDeviceDelta</S>
                <S>Get-MgDeviceExtension</S>
                <S>Get-MgDeviceExtensionCount</S>
                <S>Get-MgDeviceMemberGroup</S>
                <S>Get-MgDeviceMemberObject</S>
                <S>Get-MgDeviceMemberOf</S>
                <S>Get-MgDeviceMemberOfAsAdministrativeUnit</S>
                <S>Get-MgDeviceMemberOfAsGroup</S>
                <S>Get-MgDeviceMemberOfCount</S>
                <S>Get-MgDeviceMemberOfCountAsAdministrativeUnit</S>
                <S>Get-MgDeviceMemberOfCountAsGroup</S>
                <S>Get-MgDeviceRegisteredOwner</S>
                <S>Get-MgDeviceRegisteredOwnerAsAppRoleAssignment</S>
                <S>Get-MgDeviceRegisteredOwnerAsEndpoint</S>
                <S>Get-MgDeviceRegisteredOwnerAsServicePrincipal</S>
                <S>Get-MgDeviceRegisteredOwnerAsUser</S>
                <S>Get-MgDeviceRegisteredOwnerByRef</S>
                <S>Get-MgDeviceRegisteredOwnerCount</S>
                <S>Get-MgDeviceRegisteredOwnerCountAsAppRoleAssignment</S>
                <S>Get-MgDeviceRegisteredOwnerCountAsEndpoint</S>
                <S>Get-MgDeviceRegisteredOwnerCountAsServicePrincipal</S>
                <S>Get-MgDeviceRegisteredOwnerCountAsUser</S>
                <S>Get-MgDeviceRegisteredUser</S>
                <S>Get-MgDeviceRegisteredUserAsAppRoleAssignment</S>
                <S>Get-MgDeviceRegisteredUserAsEndpoint</S>
                <S>Get-MgDeviceRegisteredUserAsServicePrincipal</S>
                <S>Get-MgDeviceRegisteredUserAsUser</S>
                <S>Get-MgDeviceRegisteredUserByRef</S>
                <S>Get-MgDeviceRegisteredUserCount</S>
                <S>Get-MgDeviceRegisteredUserCountAsAppRoleAssignment</S>
                <S>Get-MgDeviceRegisteredUserCountAsEndpoint</S>
                <S>Get-MgDeviceRegisteredUserCountAsServicePrincipal</S>
                <S>Get-MgDeviceRegisteredUserCountAsUser</S>
                <S>Get-MgDeviceTransitiveMemberOf</S>
                <S>Get-MgDeviceTransitiveMemberOfAsAdministrativeUnit</S>
                <S>Get-MgDeviceTransitiveMemberOfAsGroup</S>
                <S>Get-MgDeviceTransitiveMemberOfCount</S>
                <S>Get-MgDeviceTransitiveMemberOfCountAsAdministrativeUnit</S>
                <S>Get-MgDeviceTransitiveMemberOfCountAsGroup</S>
                <S>Get-MgDirectory</S>
                <S>Get-MgDirectoryAdministrativeUnit</S>
                <S>Get-MgDirectoryAdministrativeUnitCount</S>
                <S>Get-MgDirectoryAdministrativeUnitDelta</S>
                <S>Get-MgDirectoryAdministrativeUnitExtension</S>
                <S>Get-MgDirectoryAdministrativeUnitExtensionCount</S>
                <S>Get-MgDirectoryAdministrativeUnitMember</S>
                <S>Get-MgDirectoryAdministrativeUnitMemberAsApplication</S>
                <S>Get-MgDirectoryAdministrativeUnitMemberAsDevice</S>
                <S>Get-MgDirectoryAdministrativeUnitMemberAsGroup</S>
                <S>Get-MgDirectoryAdministrativeUnitMemberAsOrgContact</S>
                <S>Get-MgDirectoryAdministrativeUnitMemberAsServicePrincipal</S>
                <S>Get-MgDirectoryAdministrativeUnitMemberAsUser</S>
                <S>Get-MgDirectoryAdministrativeUnitMemberByRef</S>
                <S>Get-MgDirectoryAdministrativeUnitMemberCount</S>
                <S>Get-MgDirectoryAdministrativeUnitMemberCountAsApplication</S>
                <S>Get-MgDirectoryAdministrativeUnitMemberCountAsDevice</S>
                <S>Get-MgDirectoryAdministrativeUnitMemberCountAsGroup</S>
                <S>Get-MgDirectoryAdministrativeUnitMemberCountAsOrgContact</S>
                <S>Get-MgDirectoryAdministrativeUnitMemberCountAsServicePrincipal</S>
                <S>Get-MgDirectoryAdministrativeUnitMemberCountAsUser</S>
                <S>Get-MgDirectoryAdministrativeUnitScopedRoleMember</S>
                <S>Get-MgDirectoryAdministrativeUnitScopedRoleMemberCount</S>
                <S>Get-MgDirectoryAttributeSet</S>
                <S>Get-MgDirectoryAttributeSetCount</S>
                <S>Get-MgDirectoryCustomSecurityAttributeDefinition</S>
                <S>Get-MgDirectoryCustomSecurityAttributeDefinitionAllowedValue</S>
                <S>Get-MgDirectoryCustomSecurityAttributeDefinitionAllowedValueCount</S>
                <S>Get-MgDirectoryCustomSecurityAttributeDefinitionCount</S>
                <S>Get-MgDirectoryDeletedItem</S>
                <S>Get-MgDirectoryDeletedItemAsAdministrativeUnit</S>
                <S>Get-MgDirectoryDeletedItemAsApplication</S>
                <S>Get-MgDirectoryDeletedItemAsDevice</S>
                <S>Get-MgDirectoryDeletedItemAsGroup</S>
                <S>Get-MgDirectoryDeletedItemAsServicePrincipal</S>
                <S>Get-MgDirectoryDeletedItemAsUser</S>
                <S>Get-MgDirectoryDeletedItemById</S>
                <S>Get-MgDirectoryDeletedItemCountAsAdministrativeUnit</S>
                <S>Get-MgDirectoryDeletedItemCountAsApplication</S>
                <S>Get-MgDirectoryDeletedItemCountAsDevice</S>
                <S>Get-MgDirectoryDeletedItemCountAsGroup</S>
                <S>Get-MgDirectoryDeletedItemCountAsServicePrincipal</S>
                <S>Get-MgDirectoryDeletedItemCountAsUser</S>
                <S>Get-MgDirectoryDeletedItemMemberGroup</S>
                <S>Get-MgDirectoryDeletedItemMemberObject</S>
                <S>Get-MgDirectoryDeviceLocalCredential</S>
                <S>Get-MgDirectoryDeviceLocalCredentialCount</S>
                <S>Get-MgDirectoryFederationConfiguration</S>
                <S>Get-MgDirectoryFederationConfigurationCount</S>
                <S>Get-MgDirectoryOnPremiseSynchronization</S>
                <S>Get-MgDirectoryOnPremiseSynchronizationCount</S>
                <S>Get-MgDirectoryRole</S>
                <S>Get-MgDirectoryRoleById</S>
                <S>Get-MgDirectoryRoleByRoleTemplateId</S>
                <S>Get-MgDirectoryRoleCount</S>
                <S>Get-MgDirectoryRoleDelta</S>
                <S>Get-MgDirectoryRoleMember</S>
                <S>Get-MgDirectoryRoleMemberAsApplication</S>
                <S>Get-MgDirectoryRoleMemberAsDevice</S>
                <S>Get-MgDirectoryRoleMemberAsGroup</S>
                <S>Get-MgDirectoryRoleMemberAsOrgContact</S>
                <S>Get-MgDirectoryRoleMemberAsServicePrincipal</S>
                <S>Get-MgDirectoryRoleMemberAsUser</S>
                <S>Get-MgDirectoryRoleMemberByRef</S>
                <S>Get-MgDirectoryRoleMemberCount</S>
                <S>Get-MgDirectoryRoleMemberCountAsApplication</S>
                <S>Get-MgDirectoryRoleMemberCountAsDevice</S>
                <S>Get-MgDirectoryRoleMemberCountAsGroup</S>
                <S>Get-MgDirectoryRoleMemberCountAsOrgContact</S>
                <S>Get-MgDirectoryRoleMemberCountAsServicePrincipal</S>
                <S>Get-MgDirectoryRoleMemberCountAsUser</S>
                <S>Get-MgDirectoryRoleMemberGroup</S>
                <S>Get-MgDirectoryRoleMemberObject</S>
                <S>Get-MgDirectoryRoleScopedMember</S>
                <S>Get-MgDirectoryRoleScopedMemberCount</S>
                <S>Get-MgDirectoryRoleTemplate</S>
                <S>Get-MgDirectoryRoleTemplateById</S>
                <S>Get-MgDirectoryRoleTemplateCount</S>
                <S>Get-MgDirectoryRoleTemplateDelta</S>
                <S>Get-MgDirectoryRoleTemplateMemberGroup</S>
                <S>Get-MgDirectoryRoleTemplateMemberObject</S>
                <S>Get-MgDirectorySubscription</S>
                <S>Get-MgDirectorySubscriptionByCommerceSubscriptionId</S>
                <S>Get-MgDirectorySubscriptionCount</S>
                <S>Get-MgDomain</S>
                <S>Get-MgDomainCount</S>
                <S>Get-MgDomainFederationConfiguration</S>
                <S>Get-MgDomainFederationConfigurationCount</S>
                <S>Get-MgDomainNameReference</S>
                <S>Get-MgDomainNameReferenceCount</S>
                <S>Get-MgDomainRootDomain</S>
                <S>Get-MgDomainServiceConfigurationRecord</S>
                <S>Get-MgDomainServiceConfigurationRecordCount</S>
                <S>Get-MgDomainVerificationDnsRecord</S>
                <S>Get-MgDomainVerificationDnsRecordCount</S>
                <S>Get-MgOrganization</S>
                <S>Get-MgOrganizationBranding</S>
                <S>Get-MgOrganizationBrandingBackgroundImage</S>
                <S>Get-MgOrganizationBrandingBannerLogo</S>
                <S>Get-MgOrganizationBrandingCustomCss</S>
                <S>Get-MgOrganizationBrandingFavicon</S>
                <S>Get-MgOrganizationBrandingHeaderLogo</S>
                <S>Get-MgOrganizationBrandingLocalization</S>
                <S>Get-MgOrganizationBrandingLocalizationBackgroundImage</S>
                <S>Get-MgOrganizationBrandingLocalizationBannerLogo</S>
                <S>Get-MgOrganizationBrandingLocalizationCount</S>
                <S>Get-MgOrganizationBrandingLocalizationCustomCss</S>
                <S>Get-MgOrganizationBrandingLocalizationFavicon</S>
                <S>Get-MgOrganizationBrandingLocalizationHeaderLogo</S>
                <S>Get-MgOrganizationBrandingLocalizationSquareLogo</S>
                <S>Get-MgOrganizationBrandingLocalizationSquareLogoDark</S>
                <S>Get-MgOrganizationBrandingSquareLogo</S>
                <S>Get-MgOrganizationBrandingSquareLogoDark</S>
                <S>Get-MgOrganizationById</S>
                <S>Get-MgOrganizationCount</S>
                <S>Get-MgOrganizationExtension</S>
                <S>Get-MgOrganizationExtensionCount</S>
                <S>Get-MgOrganizationMemberGroup</S>
                <S>Get-MgOrganizationMemberObject</S>
                <S>Get-MgSubscribedSku</S>
                <S>Get-MgUserScopedRoleMemberOf</S>
                <S>Get-MgUserScopedRoleMemberOfCount</S>
                <S>Invoke-MgAvailableDirectoryFederationConfigurationProviderType</S>
                <S>Invoke-MgForceDomainDelete</S>
                <S>Invoke-MgPromoteDomain</S>
                <S>Invoke-MgRetryContactServiceProvisioning</S>
                <S>New-MgAdminPeopleProfileCardProperty</S>
                <S>New-MgContact</S>
                <S>New-MgContract</S>
                <S>New-MgDevice</S>
                <S>New-MgDeviceExtension</S>
                <S>New-MgDeviceRegisteredOwnerByRef</S>
                <S>New-MgDeviceRegisteredUserByRef</S>
                <S>New-MgDirectoryAdministrativeUnit</S>
                <S>New-MgDirectoryAdministrativeUnitExtension</S>
                <S>New-MgDirectoryAdministrativeUnitMember</S>
                <S>New-MgDirectoryAdministrativeUnitMemberByRef</S>
                <S>New-MgDirectoryAdministrativeUnitScopedRoleMember</S>
                <S>New-MgDirectoryAttributeSet</S>
                <S>New-MgDirectoryCustomSecurityAttributeDefinition</S>
                <S>New-MgDirectoryCustomSecurityAttributeDefinitionAllowedValue</S>
                <S>New-MgDirectoryDeviceLocalCredential</S>
                <S>New-MgDirectoryFederationConfiguration</S>
                <S>New-MgDirectoryOnPremiseSynchronization</S>
                <S>New-MgDirectoryRole</S>
                <S>New-MgDirectoryRoleMemberByRef</S>
                <S>New-MgDirectoryRoleScopedMember</S>
                <S>New-MgDirectoryRoleTemplate</S>
                <S>New-MgDirectorySubscription</S>
                <S>New-MgDomain</S>
                <S>New-MgDomainFederationConfiguration</S>
                <S>New-MgDomainServiceConfigurationRecord</S>
                <S>New-MgDomainVerificationDnsRecord</S>
                <S>New-MgOrganization</S>
                <S>New-MgOrganizationBrandingLocalization</S>
                <S>New-MgOrganizationExtension</S>
                <S>New-MgSubscribedSku</S>
                <S>New-MgUserScopedRoleMemberOf</S>
                <S>Remove-MgAdminPeopleItemInsight</S>
                <S>Remove-MgAdminPeopleProfileCardProperty</S>
                <S>Remove-MgContact</S>
                <S>Remove-MgContract</S>
                <S>Remove-MgDevice</S>
                <S>Remove-MgDeviceByDeviceId</S>
                <S>Remove-MgDeviceExtension</S>
                <S>Remove-MgDeviceRegisteredOwnerDirectoryObjectByRef</S>
                <S>Remove-MgDeviceRegisteredUserDirectoryObjectByRef</S>
                <S>Remove-MgDirectoryAdministrativeUnit</S>
                <S>Remove-MgDirectoryAdministrativeUnitExtension</S>
                <S>Remove-MgDirectoryAdministrativeUnitMemberDirectoryObjectByRef</S>
                <S>Remove-MgDirectoryAdministrativeUnitScopedRoleMember</S>
                <S>Remove-MgDirectoryAttributeSet</S>
                <S>Remove-MgDirectoryCustomSecurityAttributeDefinition</S>
                <S>Remove-MgDirectoryCustomSecurityAttributeDefinitionAllowedValue</S>
                <S>Remove-MgDirectoryDeletedItem</S>
                <S>Remove-MgDirectoryDeviceLocalCredential</S>
                <S>Remove-MgDirectoryFederationConfiguration</S>
                <S>Remove-MgDirectoryOnPremiseSynchronization</S>
                <S>Remove-MgDirectoryRole</S>
                <S>Remove-MgDirectoryRoleByRoleTemplateId</S>
                <S>Remove-MgDirectoryRoleMemberDirectoryObjectByRef</S>
                <S>Remove-MgDirectoryRoleScopedMember</S>
                <S>Remove-MgDirectoryRoleTemplate</S>
                <S>Remove-MgDirectorySubscription</S>
                <S>Remove-MgDirectorySubscriptionByCommerceSubscriptionId</S>
                <S>Remove-MgDomain</S>
                <S>Remove-MgDomainFederationConfiguration</S>
                <S>Remove-MgDomainServiceConfigurationRecord</S>
                <S>Remove-MgDomainVerificationDnsRecord</S>
                <S>Remove-MgOrganization</S>
                <S>Remove-MgOrganizationBranding</S>
                <S>Remove-MgOrganizationBrandingBackgroundImage</S>
                <S>Remove-MgOrganizationBrandingBannerLogo</S>
                <S>Remove-MgOrganizationBrandingCustomCss</S>
                <S>Remove-MgOrganizationBrandingFavicon</S>
                <S>Remove-MgOrganizationBrandingHeaderLogo</S>
                <S>Remove-MgOrganizationBrandingLocalization</S>
                <S>Remove-MgOrganizationBrandingLocalizationBackgroundImage</S>
                <S>Remove-MgOrganizationBrandingLocalizationBannerLogo</S>
                <S>Remove-MgOrganizationBrandingLocalizationCustomCss</S>
                <S>Remove-MgOrganizationBrandingLocalizationFavicon</S>
                <S>Remove-MgOrganizationBrandingLocalizationHeaderLogo</S>
                <S>Remove-MgOrganizationBrandingLocalizationSquareLogo</S>
                <S>Remove-MgOrganizationBrandingLocalizationSquareLogoDark</S>
                <S>Remove-MgOrganizationBrandingSquareLogo</S>
                <S>Remove-MgOrganizationBrandingSquareLogoDark</S>
                <S>Remove-MgOrganizationExtension</S>
                <S>Remove-MgSubscribedSku</S>
                <S>Remove-MgUserScopedRoleMemberOf</S>
                <S>Restore-MgDirectoryDeletedItem</S>
                <S>Set-MgOrganizationBrandingBackgroundImage</S>
                <S>Set-MgOrganizationBrandingBannerLogo</S>
                <S>Set-MgOrganizationBrandingCustomCss</S>
                <S>Set-MgOrganizationBrandingFavicon</S>
                <S>Set-MgOrganizationBrandingHeaderLogo</S>
                <S>Set-MgOrganizationBrandingLocalizationBackgroundImage</S>
                <S>Set-MgOrganizationBrandingLocalizationBannerLogo</S>
                <S>Set-MgOrganizationBrandingLocalizationCustomCss</S>
                <S>Set-MgOrganizationBrandingLocalizationFavicon</S>
                <S>Set-MgOrganizationBrandingLocalizationHeaderLogo</S>
                <S>Set-MgOrganizationBrandingLocalizationSquareLogo</S>
                <S>Set-MgOrganizationBrandingLocalizationSquareLogoDark</S>
                <S>Set-MgOrganizationBrandingSquareLogo</S>
                <S>Set-MgOrganizationBrandingSquareLogoDark</S>
                <S>Set-MgOrganizationMobileDeviceManagementAuthority</S>
                <S>Test-MgContactProperty</S>
                <S>Test-MgContractProperty</S>
                <S>Test-MgDeviceProperty</S>
                <S>Test-MgDirectoryDeletedItemProperty</S>
                <S>Test-MgDirectoryRoleProperty</S>
                <S>Test-MgDirectoryRoleTemplateProperty</S>
                <S>Test-MgOrganizationProperty</S>
                <S>Update-MgAdminPeopleItemInsight</S>
                <S>Update-MgAdminPeopleProfileCardProperty</S>
                <S>Update-MgAdminPeoplePronoun</S>
                <S>Update-MgContact</S>
                <S>Update-MgContract</S>
                <S>Update-MgDevice</S>
                <S>Update-MgDeviceByDeviceId</S>
                <S>Update-MgDeviceExtension</S>
                <S>Update-MgDirectory</S>
                <S>Update-MgDirectoryAdministrativeUnit</S>
                <S>Update-MgDirectoryAdministrativeUnitExtension</S>
                <S>Update-MgDirectoryAdministrativeUnitScopedRoleMember</S>
                <S>Update-MgDirectoryAttributeSet</S>
                <S>Update-MgDirectoryCustomSecurityAttributeDefinition</S>
                <S>Update-MgDirectoryCustomSecurityAttributeDefinitionAllowedValue</S>
                <S>Update-MgDirectoryDeviceLocalCredential</S>
                <S>Update-MgDirectoryFederationConfiguration</S>
                <S>Update-MgDirectoryOnPremiseSynchronization</S>
                <S>Update-MgDirectoryRole</S>
                <S>Update-MgDirectoryRoleByRoleTemplateId</S>
                <S>Update-MgDirectoryRoleScopedMember</S>
                <S>Update-MgDirectoryRoleTemplate</S>
                <S>Update-MgDirectorySubscription</S>
                <S>Update-MgDirectorySubscriptionByCommerceSubscriptionId</S>
                <S>Update-MgDomain</S>
                <S>Update-MgDomainFederationConfiguration</S>
                <S>Update-MgDomainServiceConfigurationRecord</S>
                <S>Update-MgDomainVerificationDnsRecord</S>
                <S>Update-MgOrganization</S>
                <S>Update-MgOrganizationBranding</S>
                <S>Update-MgOrganizationBrandingLocalization</S>
                <S>Update-MgOrganizationExtension</S>
                <S>Update-MgSubscribedSku</S>
                <S>Update-MgUserScopedRoleMemberOf</S>
              </LST>
            </Obj>
          </En>
          <En>
            <S N="Key">DscResource</S>
            <Ref N="Value" RefId="4" />
          </En>
          <En>
            <S N="Key">Workflow</S>
            <Ref N="Value" RefId="4" />
          </En>
          <En>
            <S N="Key">Cmdlet</S>
            <Ref N="Value" RefId="4" />
          </En>
        </DCT>
      </Obj>
      <Nil N="PowerShellGetFormatVersion" />
      <S N="ReleaseNotes">See https://aka.ms/GraphPowerShell-Release.</S>
      <Obj N="Dependencies" RefId="6">
        <TNRef RefId="1" />
        <LST>
          <Obj RefId="7">
            <TN RefId="3">
              <T>System.Collections.Specialized.OrderedDictionary</T>
              <T>System.Object</T>
            </TN>
            <DCT>
              <En>
                <S N="Key">Name</S>
                <S N="Value">Microsoft.Graph.Authentication</S>
              </En>
              <En>
                <S N="Key">RequiredVersion</S>
                <S N="Value">2.25.0</S>
              </En>
              <En>
                <S N="Key">CanonicalId</S>
                <S N="Value">nuget:Microsoft.Graph.Authentication/[2.25.0]</S>
              </En>
            </DCT>
          </Obj>
        </LST>
      </Obj>
      <S N="RepositorySourceLocation">https://www.powershellgallery.com/api/v2</S>
      <S N="Repository">PSGallery</S>
      <S N="PackageManagementProvider">NuGet</S>
      <Obj N="AdditionalMetadata" RefId="8">
        <TN RefId="4">
          <T>System.Management.Automation.PSCustomObject</T>
          <T>System.Object</T>
        </TN>
        <MS>
          <S N="copyright">Microsoft Corporation. All rights reserved.</S>
          <S N="description">Microsoft Graph PowerShell Cmdlets</S>
          <S N="requireLicenseAcceptance">True</S>
          <S N="releaseNotes">See https://aka.ms/GraphPowerShell-Release.</S>
          <S N="isLatestVersion">True</S>
          <S N="isAbsoluteLatestVersion">True</S>
          <S N="versionDownloadCount">4847745</S>
          <S N="downloadCount">19368480</S>
          <S N="packageSize">4465382</S>
          <S N="published">11/21/2024 6:27:58 AM -05:00</S>
          <S N="created">11/21/2024 6:27:58 AM -05:00</S>
          <S N="lastUpdated">2/17/2025 9:40:00 PM -05:00</S>
          <S N="tags">Microsoft Office365 Graph PowerShell PSModule PSIncludes_Cmdlet PSEdition_Core PSEdition_Desktop PSFunction_Confirm-MgContactMemberGroup PSCommand_Confirm-MgContactMemberGroup PSFunction_Confirm-MgContactMemberObject PSCommand_Confirm-MgContactMemberObject PSFunction_Confirm-MgContractMemberGroup PSCommand_Confirm-MgContractMemberGroup PSFunction_Confirm-MgContractMemberObject PSCommand_Confirm-MgContractMemberObject PSFunction_Confirm-MgDeviceMemberGroup PSCommand_Confirm-MgDeviceMemberGroup PSFunction_Confirm-MgDeviceMemberObject PSCommand_Confirm-MgDeviceMemberObject PSFunction_Confirm-MgDirectoryDeletedItemMemberGroup PSCommand_Confirm-MgDirectoryDeletedItemMemberGroup PSFunction_Confirm-MgDirectoryDeletedItemMemberObject PSCommand_Confirm-MgDirectoryDeletedItemMemberObject PSFunction_Confirm-MgDirectoryRoleMemberGroup PSCommand_Confirm-MgDirectoryRoleMemberGroup PSFunction_Confirm-MgDirectoryRoleMemberObject PSCommand_Confirm-MgDirectoryRoleMemberObject PSFunction_Confirm-MgDirectoryRoleTemplateMemberGroup PSCommand_Confirm-MgDirectoryRoleTemplateMemberGroup PSFunction_Confirm-MgDirectoryRoleTemplateMemberObject PSCommand_Confirm-MgDirectoryRoleTemplateMemberObject PSFunction_Confirm-MgDomain PSCommand_Confirm-MgDomain PSFunction_Confirm-MgOrganizationMemberGroup PSCommand_Confirm-MgOrganizationMemberGroup PSFunction_Confirm-MgOrganizationMemberObject PSCommand_Confirm-MgOrganizationMemberObject PSFunction_Get-MgAdminPeople PSCommand_Get-MgAdminPeople PSFunction_Get-MgAdminPeopleItemInsight PSCommand_Get-MgAdminPeopleItemInsight PSFunction_Get-MgAdminPeopleProfileCardProperty PSCommand_Get-MgAdminPeopleProfileCardProperty PSFunction_Get-MgAdminPeopleProfileCardPropertyCount PSCommand_Get-MgAdminPeopleProfileCardPropertyCount PSFunction_Get-MgAdminPeoplePronoun PSCommand_Get-MgAdminPeoplePronoun PSFunction_Get-MgContact PSCommand_Get-MgContact PSFunction_Get-MgContactById PSCommand_Get-MgContactById PSFunction_Get-MgContactCount PSCommand_Get-MgContactCount PSFunction_Get-MgContactDelta PSCommand_Get-MgContactDelta PSFunction_Get-MgContactDirectReport PSCommand_Get-MgContactDirectReport PSFunction_Get-MgContactDirectReportAsOrgContact PSCommand_Get-MgContactDirectReportAsOrgContact PSFunction_Get-MgContactDirectReportAsUser PSCommand_Get-MgContactDirectReportAsUser PSFunction_Get-MgContactDirectReportCount PSCommand_Get-MgContactDirectReportCount PSFunction_Get-MgContactDirectReportCountAsOrgContact PSCommand_Get-MgContactDirectReportCountAsOrgContact PSFunction_Get-MgContactDirectReportCountAsUser PSCommand_Get-MgContactDirectReportCountAsUser PSFunction_Get-MgContactManager PSCommand_Get-MgContactManager PSFunction_Get-MgContactMemberGroup PSCommand_Get-MgContactMemberGroup PSFunction_Get-MgContactMemberObject PSCommand_Get-MgContactMemberObject PSFunction_Get-MgContactMemberOf PSCommand_Get-MgContactMemberOf PSFunction_Get-MgContactMemberOfAsAdministrativeUnit PSCommand_Get-MgContactMemberOfAsAdministrativeUnit PSFunction_Get-MgContactMemberOfAsGroup PSCommand_Get-MgContactMemberOfAsGroup PSFunction_Get-MgContactMemberOfCount PSCommand_Get-MgContactMemberOfCount PSFunction_Get-MgContactMemberOfCountAsAdministrativeUnit PSCommand_Get-MgContactMemberOfCountAsAdministrativeUnit PSFunction_Get-MgContactMemberOfCountAsGroup PSCommand_Get-MgContactMemberOfCountAsGroup PSFunction_Get-MgContactServiceProvisioningError PSCommand_Get-MgContactServiceProvisioningError PSFunction_Get-MgContactServiceProvisioningErrorCount PSCommand_Get-MgContactServiceProvisioningErrorCount PSFunction_Get-MgContactTransitiveMemberOf PSCommand_Get-MgContactTransitiveMemberOf PSFunction_Get-MgContactTransitiveMemberOfAsAdministrativeUnit PSCommand_Get-MgContactTransitiveMemberOfAsAdministrativeUnit PSFunction_Get-MgContactTransitiveMemberOfAsGroup PSCommand_Get-MgContactTransitiveMemberOfAsGroup PSFunction_Get-MgContactTransitiveMemberOfCount PSCommand_Get-MgContactTransitiveMemberOfCount PSFunction_Get-MgContactTransitiveMemberOfCountAsAdministrativeUnit PSCommand_Get-MgContactTransitiveMemberOfCountAsAdministrativeUnit PSFunction_Get-MgContactTransitiveMemberOfCountAsGroup PSCommand_Get-MgContactTransitiveMemberOfCountAsGroup PSFunction_Get-MgContract PSCommand_Get-MgContract PSFunction_Get-MgContractById PSCommand_Get-MgContractById PSFunction_Get-MgContractCount PSCommand_Get-MgContractCount PSFunction_Get-MgContractDelta PSCommand_Get-MgContractDelta PSFunction_Get-MgContractMemberGroup PSCommand_Get-MgContractMemberGroup PSFunction_Get-MgContractMemberObject PSCommand_Get-MgContractMemberObject PSFunction_Get-MgDevice PSCommand_Get-MgDevice PSFunction_Get-MgDeviceByDeviceId PSCommand_Get-MgDeviceByDeviceId PSFunction_Get-MgDeviceById PSCommand_Get-MgDeviceById PSFunction_Get-MgDeviceCount PSCommand_Get-MgDeviceCount PSFunction_Get-MgDeviceDelta PSCommand_Get-MgDeviceDelta PSFunction_Get-MgDeviceExtension PSCommand_Get-MgDeviceExtension PSFunction_Get-MgDeviceExtensionCount PSCommand_Get-MgDeviceExtensionCount PSFunction_Get-MgDeviceMemberGroup PSCommand_Get-MgDeviceMemberGroup PSFunction_Get-MgDeviceMemberObject PSCommand_Get-MgDeviceMemberObject PSFunction_Get-MgDeviceMemberOf PSCommand_Get-MgDeviceMemberOf PSFunction_Get-MgDeviceMemberOfAsAdministrativeUnit PSCommand_Get-MgDeviceMemberOfAsAdministrativeUnit PSFunction_Get-MgDeviceMemberOfAsGroup PSCommand_Get-MgDeviceMemberOfAsGroup PSFunction_Get-MgDeviceMemberOfCount PSCommand_Get-MgDeviceMemberOfCount PSFunction_Get-MgDeviceMemberOfCountAsAdministrativeUnit PSCommand_Get-MgDeviceMemberOfCountAsAdministrativeUnit PSFunction_Get-MgDeviceMemberOfCountAsGroup PSCommand_Get-MgDeviceMemberOfCountAsGroup PSFunction_Get-MgDeviceRegisteredOwner PSCommand_Get-MgDeviceRegisteredOwner PSFunction_Get-MgDeviceRegisteredOwnerAsAppRoleAssignment PSCommand_Get-MgDeviceRegisteredOwnerAsAppRoleAssignment PSFunction_Get-MgDeviceRegisteredOwnerAsEndpoint PSCommand_Get-MgDeviceRegisteredOwnerAsEndpoint PSFunction_Get-MgDeviceRegisteredOwnerAsServicePrincipal PSCommand_Get-MgDeviceRegisteredOwnerAsServicePrincipal PSFunction_Get-MgDeviceRegisteredOwnerAsUser PSCommand_Get-MgDeviceRegisteredOwnerAsUser PSFunction_Get-MgDeviceRegisteredOwnerByRef PSCommand_Get-MgDeviceRegisteredOwnerByRef PSFunction_Get-MgDeviceRegisteredOwnerCount PSCommand_Get-MgDeviceRegisteredOwnerCount PSFunction_Get-MgDeviceRegisteredOwnerCountAsAppRoleAssignment PSCommand_Get-MgDeviceRegisteredOwnerCountAsAppRoleAssignment PSFunction_Get-MgDeviceRegisteredOwnerCountAsEndpoint PSCommand_Get-MgDeviceRegisteredOwnerCountAsEndpoint PSFunction_Get-MgDeviceRegisteredOwnerCountAsServicePrincipal PSCommand_Get-MgDeviceRegisteredOwnerCountAsServicePrincipal PSFunction_Get-MgDeviceRegisteredOwnerCountAsUser PSCommand_Get-MgDeviceRegisteredOwnerCountAsUser PSFunction_Get-MgDeviceRegisteredUser PSCommand_Get-MgDeviceRegisteredUser PSFunction_Get-MgDeviceRegisteredUserAsAppRoleAssignment PSCommand_Get-MgDeviceRegisteredUserAsAppRoleAssignment PSFunction_Get-MgDeviceRegisteredUserAsEndpoint PSCommand_Get-MgDeviceRegisteredUserAsEndpoint PSFunction_Get-MgDeviceRegisteredUserAsServicePrincipal PSCommand_Get-MgDeviceRegisteredUserAsServicePrincipal PSFunction_Get-MgDeviceRegisteredUserAsUser PSCommand_Get-MgDeviceRegisteredUserAsUser PSFunction_Get-MgDeviceRegisteredUserByRef PSCommand_Get-MgDeviceRegisteredUserByRef PSFunction_Get-MgDeviceRegisteredUserCount PSCommand_Get-MgDeviceRegisteredUserCount PSFunction_Get-MgDeviceRegisteredUserCountAsAppRoleAssignment PSCommand_Get-MgDeviceRegisteredUserCountAsAppRoleAssignment PSFunction_Get-MgDeviceRegisteredUserCountAsEndpoint PSCommand_Get-MgDeviceRegisteredUserCountAsEndpoint PSFunction_Get-MgDeviceRegisteredUserCountAsServicePrincipal PSCommand_Get-MgDeviceRegisteredUserCountAsServicePrincipal PSFunction_Get-MgDeviceRegisteredUserCountAsUser PSCommand_Get-MgDeviceRegisteredUserCountAsUser PSFunction_Get-MgDeviceTransitiveMemberOf PSCommand_Get-MgDeviceTransitiveMemberOf PSFunction_Get-MgDeviceTransitiveMemberOfAsAdministrativeUnit PSCommand_Get-MgDeviceTransitiveMemberOfAsAdministrativeUnit PSFunction_Get-MgDeviceTransitiveMemberOfAsGroup PSCommand_Get-MgDeviceTransitiveMemberOfAsGroup PSFunction_Get-MgDeviceTransitiveMemberOfCount PSCommand_Get-MgDeviceTransitiveMemberOfCount PSFunction_Get-MgDeviceTransitiveMemberOfCountAsAdministrativeUnit PSCommand_Get-MgDeviceTransitiveMemberOfCountAsAdministrativeUnit PSFunction_Get-MgDeviceTransitiveMemberOfCountAsGroup PSCommand_Get-MgDeviceTransitiveMemberOfCountAsGroup PSFunction_Get-MgDirectory PSCommand_Get-MgDirectory PSFunction_Get-MgDirectoryAdministrativeUnit PSCommand_Get-MgDirectoryAdministrativeUnit PSFunction_Get-MgDirectoryAdministrativeUnitCount PSCommand_Get-MgDirectoryAdministrativeUnitCount PSFunction_Get-MgDirectoryAdministrativeUnitDelta PSCommand_Get-MgDirectoryAdministrativeUnitDelta PSFunction_Get-MgDirectoryAdministrativeUnitExtension PSCommand_Get-MgDirectoryAdministrativeUnitExtension PSFunction_Get-MgDirectoryAdministrativeUnitExtensionCount PSCommand_Get-MgDirectoryAdministrativeUnitExtensionCount PSFunction_Get-MgDirectoryAdministrativeUnitMember PSCommand_Get-MgDirectoryAdministrativeUnitMember PSFunction_Get-MgDirectoryAdministrativeUnitMemberAsApplication PSCommand_Get-MgDirectoryAdministrativeUnitMemberAsApplication PSFunction_Get-MgDirectoryAdministrativeUnitMemberAsDevice PSCommand_Get-MgDirectoryAdministrativeUnitMemberAsDevice PSFunction_Get-MgDirectoryAdministrativeUnitMemberAsGroup PSCommand_Get-MgDirectoryAdministrativeUnitMemberAsGroup PSFunction_Get-MgDirectoryAdministrativeUnitMemberAsOrgContact PSCommand_Get-MgDirectoryAdministrativeUnitMemberAsOrgContact PSFunction_Get-MgDirectoryAdministrativeUnitMemberAsServicePrincipal PSCommand_Get-MgDirectoryAdministrativeUnitMemberAsServicePrincipal PSFunction_Get-MgDirectoryAdministrativeUnitMemberAsUser PSCommand_Get-MgDirectoryAdministrativeUnitMemberAsUser PSFunction_Get-MgDirectoryAdministrativeUnitMemberByRef PSCommand_Get-MgDirectoryAdministrativeUnitMemberByRef PSFunction_Get-MgDirectoryAdministrativeUnitMemberCount PSCommand_Get-MgDirectoryAdministrativeUnitMemberCount PSFunction_Get-MgDirectoryAdministrativeUnitMemberCountAsApplication PSCommand_Get-MgDirectoryAdministrativeUnitMemberCountAsApplication PSFunction_Get-MgDirectoryAdministrativeUnitMemberCountAsDevice PSCommand_Get-MgDirectoryAdministrativeUnitMemberCountAsDevice PSFunction_Get-MgDirectoryAdministrativeUnitMemberCountAsGroup PSCommand_Get-MgDirectoryAdministrativeUnitMemberCountAsGroup PSFunction_Get-MgDirectoryAdministrativeUnitMemberCountAsOrgContact PSCommand_Get-MgDirectoryAdministrativeUnitMemberCountAsOrgContact PSFunction_Get-MgDirectoryAdministrativeUnitMemberCountAsServicePrincipal PSCommand_Get-MgDirectoryAdministrativeUnitMemberCountAsServicePrincipal PSFunction_Get-MgDirectoryAdministrativeUnitMemberCountAsUser PSCommand_Get-MgDirectoryAdministrativeUnitMemberCountAsUser PSFunction_Get-MgDirectoryAdministrativeUnitScopedRoleMember PSCommand_Get-MgDirectoryAdministrativeUnitScopedRoleMember PSFunction_Get-MgDirectoryAdministrativeUnitScopedRoleMemberCount PSCommand_Get-MgDirectoryAdministrativeUnitScopedRoleMemberCount PSFunction_Get-MgDirectoryAttributeSet PSCommand_Get-MgDirectoryAttributeSet PSFunction_Get-MgDirectoryAttributeSetCount PSCommand_Get-MgDirectoryAttributeSetCount PSFunction_Get-MgDirectoryCustomSecurityAttributeDefinition PSCommand_Get-MgDirectoryCustomSecurityAttributeDefinition PSFunction_Get-MgDirectoryCustomSecurityAttributeDefinitionAllowedValue PSCommand_Get-MgDirectoryCustomSecurityAttributeDefinitionAllowedValue PSFunction_Get-MgDirectoryCustomSecurityAttributeDefinitionAllowedValueCount PSCommand_Get-MgDirectoryCustomSecurityAttributeDefinitionAllowedValueCount PSFunction_Get-MgDirectoryCustomSecurityAttributeDefinitionCount PSCommand_Get-MgDirectoryCustomSecurityAttributeDefinitionCount PSFunction_Get-MgDirectoryDeletedItem PSCommand_Get-MgDirectoryDeletedItem PSFunction_Get-MgDirectoryDeletedItemAsAdministrativeUnit PSCommand_Get-MgDirectoryDeletedItemAsAdministrativeUnit PSFunction_Get-MgDirectoryDeletedItemAsApplication PSCommand_Get-MgDirectoryDeletedItemAsApplication PSFunction_Get-MgDirectoryDeletedItemAsDevice PSCommand_Get-MgDirectoryDeletedItemAsDevice PSFunction_Get-MgDirectoryDeletedItemAsGroup PSCommand_Get-MgDirectoryDeletedItemAsGroup PSFunction_Get-MgDirectoryDeletedItemAsServicePrincipal PSCommand_Get-MgDirectoryDeletedItemAsServicePrincipal PSFunction_Get-MgDirectoryDeletedItemAsUser PSCommand_Get-MgDirectoryDeletedItemAsUser PSFunction_Get-MgDirectoryDeletedItemById PSCommand_Get-MgDirectoryDeletedItemById PSFunction_Get-MgDirectoryDeletedItemCountAsAdministrativeUnit PSCommand_Get-MgDirectoryDeletedItemCountAsAdministrativeUnit PSFunction_Get-MgDirectoryDeletedItemCountAsApplication PSCommand_Get-MgDirectoryDeletedItemCountAsApplication PSFunction_Get-MgDirectoryDeletedItemCountAsDevice PSCommand_Get-MgDirectoryDeletedItemCountAsDevice PSFunction_Get-MgDirectoryDeletedItemCountAsGroup PSCommand_Get-MgDirectoryDeletedItemCountAsGroup PSFunction_Get-MgDirectoryDeletedItemCountAsServicePrincipal PSCommand_Get-MgDirectoryDeletedItemCountAsServicePrincipal PSFunction_Get-MgDirectoryDeletedItemCountAsUser PSCommand_Get-MgDirectoryDeletedItemCountAsUser PSFunction_Get-MgDirectoryDeletedItemMemberGroup PSCommand_Get-MgDirectoryDeletedItemMemberGroup PSFunction_Get-MgDirectoryDeletedItemMemberObject PSCommand_Get-MgDirectoryDeletedItemMemberObject PSFunction_Get-MgDirectoryDeviceLocalCredential PSCommand_Get-MgDirectoryDeviceLocalCredential PSFunction_Get-MgDirectoryDeviceLocalCredentialCount PSCommand_Get-MgDirectoryDeviceLocalCredentialCount PSFunction_Get-MgDirectoryFederationConfiguration PSCommand_Get-MgDirectoryFederationConfiguration PSFunction_Get-MgDirectoryFederationConfigurationCount PSCommand_Get-MgDirectoryFederationConfigurationCount PSFunction_Get-MgDirectoryOnPremiseSynchronization PSCommand_Get-MgDirectoryOnPremiseSynchronization PSFunction_Get-MgDirectoryOnPremiseSynchronizationCount PSCommand_Get-MgDirectoryOnPremiseSynchronizationCount PSFunction_Get-MgDirectoryRole PSCommand_Get-MgDirectoryRole PSFunction_Get-MgDirectoryRoleById PSCommand_Get-MgDirectoryRoleById PSFunction_Get-MgDirectoryRoleByRoleTemplateId PSCommand_Get-MgDirectoryRoleByRoleTemplateId PSFunction_Get-MgDirectoryRoleCount PSCommand_Get-MgDirectoryRoleCount PSFunction_Get-MgDirectoryRoleDelta PSCommand_Get-MgDirectoryRoleDelta PSFunction_Get-MgDirectoryRoleMember PSCommand_Get-MgDirectoryRoleMember PSFunction_Get-MgDirectoryRoleMemberAsApplication PSCommand_Get-MgDirectoryRoleMemberAsApplication PSFunction_Get-MgDirectoryRoleMemberAsDevice PSCommand_Get-MgDirectoryRoleMemberAsDevice PSFunction_Get-MgDirectoryRoleMemberAsGroup PSCommand_Get-MgDirectoryRoleMemberAsGroup PSFunction_Get-MgDirectoryRoleMemberAsOrgContact PSCommand_Get-MgDirectoryRoleMemberAsOrgContact PSFunction_Get-MgDirectoryRoleMemberAsServicePrincipal PSCommand_Get-MgDirectoryRoleMemberAsServicePrincipal PSFunction_Get-MgDirectoryRoleMemberAsUser PSCommand_Get-MgDirectoryRoleMemberAsUser PSFunction_Get-MgDirectoryRoleMemberByRef PSCommand_Get-MgDirectoryRoleMemberByRef PSFunction_Get-MgDirectoryRoleMemberCount PSCommand_Get-MgDirectoryRoleMemberCount PSFunction_Get-MgDirectoryRoleMemberCountAsApplication PSCommand_Get-MgDirectoryRoleMemberCountAsApplication PSFunction_Get-MgDirectoryRoleMemberCountAsDevice PSCommand_Get-MgDirectoryRoleMemberCountAsDevice PSFunction_Get-MgDirectoryRoleMemberCountAsGroup PSCommand_Get-MgDirectoryRoleMemberCountAsGroup PSFunction_Get-MgDirectoryRoleMemberCountAsOrgContact PSCommand_Get-MgDirectoryRoleMemberCountAsOrgContact PSFunction_Get-MgDirectoryRoleMemberCountAsServicePrincipal PSCommand_Get-MgDirectoryRoleMemberCountAsServicePrincipal PSFunction_Get-MgDirectoryRoleMemberCountAsUser PSCommand_Get-MgDirectoryRoleMemberCountAsUser PSFunction_Get-MgDirectoryRoleMemberGroup PSCommand_Get-MgDirectoryRoleMemberGroup PSFunction_Get-MgDirectoryRoleMemberObject PSCommand_Get-MgDirectoryRoleMemberObject PSFunction_Get-MgDirectoryRoleScopedMember PSCommand_Get-MgDirectoryRoleScopedMember PSFunction_Get-MgDirectoryRoleScopedMemberCount PSCommand_Get-MgDirectoryRoleScopedMemberCount PSFunction_Get-MgDirectoryRoleTemplate PSCommand_Get-MgDirectoryRoleTemplate PSFunction_Get-MgDirectoryRoleTemplateById PSCommand_Get-MgDirectoryRoleTemplateById PSFunction_Get-MgDirectoryRoleTemplateCount PSCommand_Get-MgDirectoryRoleTemplateCount PSFunction_Get-MgDirectoryRoleTemplateDelta PSCommand_Get-MgDirectoryRoleTemplateDelta PSFunction_Get-MgDirectoryRoleTemplateMemberGroup PSCommand_Get-MgDirectoryRoleTemplateMemberGroup PSFunction_Get-MgDirectoryRoleTemplateMemberObject PSCommand_Get-MgDirectoryRoleTemplateMemberObject PSFunction_Get-MgDirectorySubscription PSCommand_Get-MgDirectorySubscription PSFunction_Get-MgDirectorySubscriptionByCommerceSubscriptionId PSCommand_Get-MgDirectorySubscriptionByCommerceSubscriptionId PSFunction_Get-MgDirectorySubscriptionCount PSCommand_Get-MgDirectorySubscriptionCount PSFunction_Get-MgDomain PSCommand_Get-MgDomain PSFunction_Get-MgDomainCount PSCommand_Get-MgDomainCount PSFunction_Get-MgDomainFederationConfiguration PSCommand_Get-MgDomainFederationConfiguration PSFunction_Get-MgDomainFederationConfigurationCount PSCommand_Get-MgDomainFederationConfigurationCount PSFunction_Get-MgDomainNameReference PSCommand_Get-MgDomainNameReference PSFunction_Get-MgDomainNameReferenceCount PSCommand_Get-MgDomainNameReferenceCount PSFunction_Get-MgDomainRootDomain PSCommand_Get-MgDomainRootDomain PSFunction_Get-MgDomainServiceConfigurationRecord PSCommand_Get-MgDomainServiceConfigurationRecord PSFunction_Get-MgDomainServiceConfigurationRecordCount PSCommand_Get-MgDomainServiceConfigurationRecordCount PSFunction_Get-MgDomainVerificationDnsRecord PSCommand_Get-MgDomainVerificationDnsRecord PSFunction_Get-MgDomainVerificationDnsRecordCount PSCommand_Get-MgDomainVerificationDnsRecordCount PSFunction_Get-MgOrganization PSCommand_Get-MgOrganization PSFunction_Get-MgOrganizationBranding PSCommand_Get-MgOrganizationBranding PSFunction_Get-MgOrganizationBrandingBackgroundImage PSCommand_Get-MgOrganizationBrandingBackgroundImage PSFunction_Get-MgOrganizationBrandingBannerLogo PSCommand_Get-MgOrganizationBrandingBannerLogo PSFunction_Get-MgOrganizationBrandingCustomCss PSCommand_Get-MgOrganizationBrandingCustomCss PSFunction_Get-MgOrganizationBrandingFavicon PSCommand_Get-MgOrganizationBrandingFavicon PSFunction_Get-MgOrganizationBrandingHeaderLogo PSCommand_Get-MgOrganizationBrandingHeaderLogo PSFunction_Get-MgOrganizationBrandingLocalization PSCommand_Get-MgOrganizationBrandingLocalization PSFunction_Get-MgOrganizationBrandingLocalizationBackgroundImage PSCommand_Get-MgOrganizationBrandingLocalizationBackgroundImage PSFunction_Get-MgOrganizationBrandingLocalizationBannerLogo PSCommand_Get-MgOrganizationBrandingLocalizationBannerLogo PSFunction_Get-MgOrganizationBrandingLocalizationCount PSCommand_Get-MgOrganizationBrandingLocalizationCount PSFunction_Get-MgOrganizationBrandingLocalizationCustomCss PSCommand_Get-MgOrganizationBrandingLocalizationCustomCss PSFunction_Get-MgOrganizationBrandingLocalizationFavicon PSCommand_Get-MgOrganizationBrandingLocalizationFavicon PSFunction_Get-MgOrganizationBrandingLocalizationHeaderLogo PSCommand_Get-MgOrganizationBrandingLocalizationHeaderLogo PSFunction_Get-MgOrganizationBrandingLocalizationSquareLogo PSCommand_Get-MgOrganizationBrandingLocalizationSquareLogo PSFunction_Get-MgOrganizationBrandingLocalizationSquareLogoDark PSCommand_Get-MgOrganizationBrandingLocalizationSquareLogoDark PSFunction_Get-MgOrganizationBrandingSquareLogo PSCommand_Get-MgOrganizationBrandingSquareLogo PSFunction_Get-MgOrganizationBrandingSquareLogoDark PSCommand_Get-MgOrganizationBrandingSquareLogoDark PSFunction_Get-MgOrganizationById PSCommand_Get-MgOrganizationById PSFunction_Get-MgOrganizationCount PSCommand_Get-MgOrganizationCount PSFunction_Get-MgOrganizationExtension PSCommand_Get-MgOrganizationExtension PSFunction_Get-MgOrganizationExtensionCount PSCommand_Get-MgOrganizationExtensionCount PSFunction_Get-MgOrganizationMemberGroup PSCommand_Get-MgOrganizationMemberGroup PSFunction_Get-MgOrganizationMemberObject PSCommand_Get-MgOrganizationMemberObject PSFunction_Get-MgSubscribedSku PSCommand_Get-MgSubscribedSku PSFunction_Get-MgUserScopedRoleMemberOf PSCommand_Get-MgUserScopedRoleMemberOf PSFunction_Get-MgUserScopedRoleMemberOfCount PSCommand_Get-MgUserScopedRoleMemberOfCount PSFunction_Invoke-MgAvailableDirectoryFederationConfigurationProviderType PSCommand_Invoke-MgAvailableDirectoryFederationConfigurationProviderType PSFunction_Invoke-MgForceDomainDelete PSCommand_Invoke-MgForceDomainDelete PSFunction_Invoke-MgPromoteDomain PSCommand_Invoke-MgPromoteDomain PSFunction_Invoke-MgRetryContactServiceProvisioning PSCommand_Invoke-MgRetryContactServiceProvisioning PSFunction_New-MgAdminPeopleProfileCardProperty PSCommand_New-MgAdminPeopleProfileCardProperty PSFunction_New-MgContact PSCommand_New-MgContact PSFunction_New-MgContract PSCommand_New-MgContract PSFunction_New-MgDevice PSCommand_New-MgDevice PSFunction_New-MgDeviceExtension PSCommand_New-MgDeviceExtension PSFunction_New-MgDeviceRegisteredOwnerByRef PSCommand_New-MgDeviceRegisteredOwnerByRef PSFunction_New-MgDeviceRegisteredUserByRef PSCommand_New-MgDeviceRegisteredUserByRef PSFunction_New-MgDirectoryAdministrativeUnit PSCommand_New-MgDirectoryAdministrativeUnit PSFunction_New-MgDirectoryAdministrativeUnitExtension PSCommand_New-MgDirectoryAdministrativeUnitExtension PSFunction_New-MgDirectoryAdministrativeUnitMember PSCommand_New-MgDirectoryAdministrativeUnitMember PSFunction_New-MgDirectoryAdministrativeUnitMemberByRef PSCommand_New-MgDirectoryAdministrativeUnitMemberByRef PSFunction_New-MgDirectoryAdministrativeUnitScopedRoleMember PSCommand_New-MgDirectoryAdministrativeUnitScopedRoleMember PSFunction_New-MgDirectoryAttributeSet PSCommand_New-MgDirectoryAttributeSet PSFunction_New-MgDirectoryCustomSecurityAttributeDefinition PSCommand_New-MgDirectoryCustomSecurityAttributeDefinition PSFunction_New-MgDirectoryCustomSecurityAttributeDefinitionAllowedValue PSCommand_New-MgDirectoryCustomSecurityAttributeDefinitionAllowedValue PSFunction_New-MgDirectoryDeviceLocalCredential PSCommand_New-MgDirectoryDeviceLocalCredential PSFunction_New-MgDirectoryFederationConfiguration PSCommand_New-MgDirectoryFederationConfiguration PSFunction_New-MgDirectoryOnPremiseSynchronization PSCommand_New-MgDirectoryOnPremiseSynchronization PSFunction_New-MgDirectoryRole PSCommand_New-MgDirectoryRole PSFunction_New-MgDirectoryRoleMemberByRef PSCommand_New-MgDirectoryRoleMemberByRef PSFunction_New-MgDirectoryRoleScopedMember PSCommand_New-MgDirectoryRoleScopedMember PSFunction_New-MgDirectoryRoleTemplate PSCommand_New-MgDirectoryRoleTemplate PSFunction_New-MgDirectorySubscription PSCommand_New-MgDirectorySubscription PSFunction_New-MgDomain PSCommand_New-MgDomain PSFunction_New-MgDomainFederationConfiguration PSCommand_New-MgDomainFederationConfiguration PSFunction_New-MgDomainServiceConfigurationRecord PSCommand_New-MgDomainServiceConfigurationRecord PSFunction_New-MgDomainVerificationDnsRecord PSCommand_New-MgDomainVerificationDnsRecord PSFunction_New-MgOrganization PSCommand_New-MgOrganization PSFunction_New-MgOrganizationBrandingLocalization PSCommand_New-MgOrganizationBrandingLocalization PSFunction_New-MgOrganizationExtension PSCommand_New-MgOrganizationExtension PSFunction_New-MgSubscribedSku PSCommand_New-MgSubscribedSku PSFunction_New-MgUserScopedRoleMemberOf PSCommand_New-MgUserScopedRoleMemberOf PSFunction_Remove-MgAdminPeopleItemInsight PSCommand_Remove-MgAdminPeopleItemInsight PSFunction_Remove-MgAdminPeopleProfileCardProperty PSCommand_Remove-MgAdminPeopleProfileCardProperty PSFunction_Remove-MgContact PSCommand_Remove-MgContact PSFunction_Remove-MgContract PSCommand_Remove-MgContract PSFunction_Remove-MgDevice PSCommand_Remove-MgDevice PSFunction_Remove-MgDeviceByDeviceId PSCommand_Remove-MgDeviceByDeviceId PSFunction_Remove-MgDeviceExtension PSCommand_Remove-MgDeviceExtension PSFunction_Remove-MgDeviceRegisteredOwnerDirectoryObjectByRef PSCommand_Remove-MgDeviceRegisteredOwnerDirectoryObjectByRef PSFunction_Remove-MgDeviceRegisteredUserDirectoryObjectByRef PSCommand_Remove-MgDeviceRegisteredUserDirectoryObjectByRef PSFunction_Remove-MgDirectoryAdministrativeUnit PSCommand_Remove-MgDirectoryAdministrativeUnit PSFunction_Remove-MgDirectoryAdministrativeUnitExtension PSCommand_Remove-MgDirectoryAdministrativeUnitExtension PSFunction_Remove-MgDirectoryAdministrativeUnitMemberDirectoryObjectByRef PSCommand_Remove-MgDirectoryAdministrativeUnitMemberDirectoryObjectByRef PSFunction_Remove-MgDirectoryAdministrativeUnitScopedRoleMember PSCommand_Remove-MgDirectoryAdministrativeUnitScopedRoleMember PSFunction_Remove-MgDirectoryAttributeSet PSCommand_Remove-MgDirectoryAttributeSet PSFunction_Remove-MgDirectoryCustomSecurityAttributeDefinition PSCommand_Remove-MgDirectoryCustomSecurityAttributeDefinition PSFunction_Remove-MgDirectoryCustomSecurityAttributeDefinitionAllowedValue PSCommand_Remove-MgDirectoryCustomSecurityAttributeDefinitionAllowedValue PSFunction_Remove-MgDirectoryDeletedItem PSCommand_Remove-MgDirectoryDeletedItem PSFunction_Remove-MgDirectoryDeviceLocalCredential PSCommand_Remove-MgDirectoryDeviceLocalCredential PSFunction_Remove-MgDirectoryFederationConfiguration PSCommand_Remove-MgDirectoryFederationConfiguration PSFunction_Remove-MgDirectoryOnPremiseSynchronization PSCommand_Remove-MgDirectoryOnPremiseSynchronization PSFunction_Remove-MgDirectoryRole PSCommand_Remove-MgDirectoryRole PSFunction_Remove-MgDirectoryRoleByRoleTemplateId PSCommand_Remove-MgDirectoryRoleByRoleTemplateId PSFunction_Remove-MgDirectoryRoleMemberDirectoryObjectByRef PSCommand_Remove-MgDirectoryRoleMemberDirectoryObjectByRef PSFunction_Remove-MgDirectoryRoleScopedMember PSCommand_Remove-MgDirectoryRoleScopedMember PSFunction_Remove-MgDirectoryRoleTemplate PSCommand_Remove-MgDirectoryRoleTemplate PSFunction_Remove-MgDirectorySubscription PSCommand_Remove-MgDirectorySubscription PSFunction_Remove-MgDirectorySubscriptionByCommerceSubscriptionId PSCommand_Remove-MgDirectorySubscriptionByCommerceSubscriptionId PSFunction_Remove-MgDomain PSCommand_Remove-MgDomain PSFunction_Remove-MgDomainFederationConfiguration PSCommand_Remove-MgDomainFederationConfiguration PSFunction_Remove-MgDomainServiceConfigurationRecord PSCommand_Remove-MgDomainServiceConfigurationRecord PSFunction_Remove-MgDomainVerificationDnsRecord PSCommand_Remove-MgDomainVerificationDnsRecord PSFunction_Remove-MgOrganization PSCommand_Remove-MgOrganization PSFunction_Remove-MgOrganizationBranding PSCommand_Remove-MgOrganizationBranding PSFunction_Remove-MgOrganizationBrandingBackgroundImage PSCommand_Remove-MgOrganizationBrandingBackgroundImage PSFunction_Remove-MgOrganizationBrandingBannerLogo PSCommand_Remove-MgOrganizationBrandingBannerLogo PSFunction_Remove-MgOrganizationBrandingCustomCss PSCommand_Remove-MgOrganizationBrandingCustomCss PSFunction_Remove-MgOrganizationBrandingFavicon PSCommand_Remove-MgOrganizationBrandingFavicon PSFunction_Remove-MgOrganizationBrandingHeaderLogo PSCommand_Remove-MgOrganizationBrandingHeaderLogo PSFunction_Remove-MgOrganizationBrandingLocalization PSCommand_Remove-MgOrganizationBrandingLocalization PSFunction_Remove-MgOrganizationBrandingLocalizationBackgroundImage PSCommand_Remove-MgOrganizationBrandingLocalizationBackgroundImage PSFunction_Remove-MgOrganizationBrandingLocalizationBannerLogo PSCommand_Remove-MgOrganizationBrandingLocalizationBannerLogo PSFunction_Remove-MgOrganizationBrandingLocalizationCustomCss PSCommand_Remove-MgOrganizationBrandingLocalizationCustomCss PSFunction_Remove-MgOrganizationBrandingLocalizationFavicon PSCommand_Remove-MgOrganizationBrandingLocalizationFavicon PSFunction_Remove-MgOrganizationBrandingLocalizationHeaderLogo PSCommand_Remove-MgOrganizationBrandingLocalizationHeaderLogo PSFunction_Remove-MgOrganizationBrandingLocalizationSquareLogo PSCommand_Remove-MgOrganizationBrandingLocalizationSquareLogo PSFunction_Remove-MgOrganizationBrandingLocalizationSquareLogoDark PSCommand_Remove-MgOrganizationBrandingLocalizationSquareLogoDark PSFunction_Remove-MgOrganizationBrandingSquareLogo PSCommand_Remove-MgOrganizationBrandingSquareLogo PSFunction_Remove-MgOrganizationBrandingSquareLogoDark PSCommand_Remove-MgOrganizationBrandingSquareLogoDark PSFunction_Remove-MgOrganizationExtension PSCommand_Remove-MgOrganizationExtension PSFunction_Remove-MgSubscribedSku PSCommand_Remove-MgSubscribedSku PSFunction_Remove-MgUserScopedRoleMemberOf PSCommand_Remove-MgUserScopedRoleMemberOf PSFunction_Restore-MgDirectoryDeletedItem PSCommand_Restore-MgDirectoryDeletedItem PSFunction_Set-MgOrganizationBrandingBackgroundImage PSCommand_Set-MgOrganizationBrandingBackgroundImage PSFunction_Set-MgOrganizationBrandingBannerLogo PSCommand_Set-MgOrganizationBrandingBannerLogo PSFunction_Set-MgOrganizationBrandingCustomCss PSCommand_Set-MgOrganizationBrandingCustomCss PSFunction_Set-MgOrganizationBrandingFavicon PSCommand_Set-MgOrganizationBrandingFavicon PSFunction_Set-MgOrganizationBrandingHeaderLogo PSCommand_Set-MgOrganizationBrandingHeaderLogo PSFunction_Set-MgOrganizationBrandingLocalizationBackgroundImage PSCommand_Set-MgOrganizationBrandingLocalizationBackgroundImage PSFunction_Set-MgOrganizationBrandingLocalizationBannerLogo PSCommand_Set-MgOrganizationBrandingLocalizationBannerLogo PSFunction_Set-MgOrganizationBrandingLocalizationCustomCss PSCommand_Set-MgOrganizationBrandingLocalizationCustomCss PSFunction_Set-MgOrganizationBrandingLocalizationFavicon PSCommand_Set-MgOrganizationBrandingLocalizationFavicon PSFunction_Set-MgOrganizationBrandingLocalizationHeaderLogo PSCommand_Set-MgOrganizationBrandingLocalizationHeaderLogo PSFunction_Set-MgOrganizationBrandingLocalizationSquareLogo PSCommand_Set-MgOrganizationBrandingLocalizationSquareLogo PSFunction_Set-MgOrganizationBrandingLocalizationSquareLogoDark PSCommand_Set-MgOrganizationBrandingLocalizationSquareLogoDark PSFunction_Set-MgOrganizationBrandingSquareLogo PSCommand_Set-MgOrganizationBrandingSquareLogo PSFunction_Set-MgOrganizationBrandingSquareLogoDark PSCommand_Set-MgOrganizationBrandingSquareLogoDark PSFunction_Set-MgOrganizationMobileDeviceManagementAuthority PSCommand_Set-MgOrganizationMobileDeviceManagementAuthority PSFunction_Test-MgContactProperty PSCommand_Test-MgContactProperty PSFunction_Test-MgContractProperty PSCommand_Test-MgContractProperty PSFunction_Test-MgDeviceProperty PSCommand_Test-MgDeviceProperty PSFunction_Test-MgDirectoryDeletedItemProperty PSCommand_Test-MgDirectoryDeletedItemProperty PSFunction_Test-MgDirectoryRoleProperty PSCommand_Test-MgDirectoryRoleProperty PSFunction_Test-MgDirectoryRoleTemplateProperty PSCommand_Test-MgDirectoryRoleTemplateProperty PSFunction_Test-MgOrganizationProperty PSCommand_Test-MgOrganizationProperty PSFunction_Update-MgAdminPeopleItemInsight PSCommand_Update-MgAdminPeopleItemInsight PSFunction_Update-MgAdminPeopleProfileCardProperty PSCommand_Update-MgAdminPeopleProfileCardProperty PSFunction_Update-MgAdminPeoplePronoun PSCommand_Update-MgAdminPeoplePronoun PSFunction_Update-MgContact PSCommand_Update-MgContact PSFunction_Update-MgContract PSCommand_Update-MgContract PSFunction_Update-MgDevice PSCommand_Update-MgDevice PSFunction_Update-MgDeviceByDeviceId PSCommand_Update-MgDeviceByDeviceId PSFunction_Update-MgDeviceExtension PSCommand_Update-MgDeviceExtension PSFunction_Update-MgDirectory PSCommand_Update-MgDirectory PSFunction_Update-MgDirectoryAdministrativeUnit PSCommand_Update-MgDirectoryAdministrativeUnit PSFunction_Update-MgDirectoryAdministrativeUnitExtension PSCommand_Update-MgDirectoryAdministrativeUnitExtension PSFunction_Update-MgDirectoryAdministrativeUnitScopedRoleMember PSCommand_Update-MgDirectoryAdministrativeUnitScopedRoleMember PSFunction_Update-MgDirectoryAttributeSet PSCommand_Update-MgDirectoryAttributeSet PSFunction_Update-MgDirectoryCustomSecurityAttributeDefinition PSCommand_Update-MgDirectoryCustomSecurityAttributeDefinition PSFunction_Update-MgDirectoryCustomSecurityAttributeDefinitionAllowedValue PSCommand_Update-MgDirectoryCustomSecurityAttributeDefinitionAllowedValue PSFunction_Update-MgDirectoryDeviceLocalCredential PSCommand_Update-MgDirectoryDeviceLocalCredential PSFunction_Update-MgDirectoryFederationConfiguration PSCommand_Update-MgDirectoryFederationConfiguration PSFunction_Update-MgDirectoryOnPremiseSynchronization PSCommand_Update-MgDirectoryOnPremiseSynchronization PSFunction_Update-MgDirectoryRole PSCommand_Update-MgDirectoryRole PSFunction_Update-MgDirectoryRoleByRoleTemplateId PSCommand_Update-MgDirectoryRoleByRoleTemplateId PSFunction_Update-MgDirectoryRoleScopedMember PSCommand_Update-MgDirectoryRoleScopedMember PSFunction_Update-MgDirectoryRoleTemplate PSCommand_Update-MgDirectoryRoleTemplate PSFunction_Update-MgDirectorySubscription PSCommand_Update-MgDirectorySubscription PSFunction_Update-MgDirectorySubscriptionByCommerceSubscriptionId PSCommand_Update-MgDirectorySubscriptionByCommerceSubscriptionId PSFunction_Update-MgDomain PSCommand_Update-MgDomain PSFunction_Update-MgDomainFederationConfiguration PSCommand_Update-MgDomainFederationConfiguration PSFunction_Update-MgDomainServiceConfigurationRecord PSCommand_Update-MgDomainServiceConfigurationRecord PSFunction_Update-MgDomainVerificationDnsRecord PSCommand_Update-MgDomainVerificationDnsRecord PSFunction_Update-MgOrganization PSCommand_Update-MgOrganization PSFunction_Update-MgOrganizationBranding PSCommand_Update-MgOrganizationBranding PSFunction_Update-MgOrganizationBrandingLocalization PSCommand_Update-MgOrganizationBrandingLocalization PSFunction_Update-MgOrganizationExtension PSCommand_Update-MgOrganizationExtension PSFunction_Update-MgSubscribedSku PSCommand_Update-MgSubscribedSku PSFunction_Update-MgUserScopedRoleMemberOf PSCommand_Update-MgUserScopedRoleMemberOf PSIncludes_Function</S>
          <S N="developmentDependency">False</S>
          <S N="updated">2025-02-17T21:40:00Z</S>
          <S N="NormalizedVersion">2.25.0</S>
          <S N="Authors">Microsoft Corporation</S>
          <S N="IsPrerelease">false</S>
          <S N="ItemType">Module</S>
          <S N="FileList">Microsoft.Graph.Identity.DirectoryManagement.nuspec|Microsoft.Graph.Identity.DirectoryManagement.format.ps1xml|Microsoft.Graph.Identity.DirectoryManagement.psd1|Microsoft.Graph.Identity.DirectoryManagement.psm1|bin\Microsoft.Graph.Identity.DirectoryManagement.private.dll|bin\Microsoft.Graph.Identity.DirectoryManagement.private.deps.json|internal\Microsoft.Graph.Identity.DirectoryManagement.internal.psm1|custom\Microsoft.Graph.Identity.DirectoryManagement.custom.psm1|exports\ProxyCmdletDefinitions.ps1|utils\Unprotect-SecureString.ps1|.signature.p7s</S>
          <S N="GUID">c767240d-585c-42cb-bb2f-6e76e6d639d4</S>
          <S N="PowerShellVersion">5.1</S>
          <S N="DotNetFrameworkVersion">4.7.2</S>
          <S N="CompanyName">Microsoft Corporation</S>
        </MS>
      </Obj>
      <S N="InstalledLocation">C:\Users\zuhai\Downloads\Dell\script\modules\Microsoft.Graph.Identity.DirectoryManagement\2.25.0</S>
    </MS>
  </Obj>
</Objs>
